{
  "type": "immersiveengineering:mineral_mix",
  "dimensions": [
    "minecraft:overworld"
  ],
  "fail_chance": 0.05,
  "ores": [
    {
      "chance": 1,
      "output": {
        "item": "tfc:ore/bituminous_coal"
      }
    },
    {
      "chance": 0.2,
      "conditions": [
        {
          "type": "forge:not",
          "value": {
            "type": "forge:tag_empty",
            "tag": "forge:dusts/phosphorus"
          }
        }
      ],
      "output": {
        "tag": "forge:dusts/phosphorus"
      }
    }
  ],
  "spoils": [
    {
      "chance": 0.2,
      "output": {
        "item": "tfc:rock/gravel/limestone"
      }
    },
    {
      "chance": 0.8,
      "output": {
        "item": "tfc:rock/cobble/limestone"
      }
    }
  ],
  "weight": 25
}