{
  "type": "immersiveengineering:mineral_mix",
  "dimensions": [
    "minecraft:overworld"
  ],
  "fail_chance": 0.05,
  "ores": [
    {
      "chance": 0.15,
      "output": {
        "item": "tfc_ie_addon:ore/rich_galena"
      }
    },
    {
      "chance": 0.6,
      "output": {
        "item": "tfc_ie_addon:ore/normal_galena"
      }
    },
    {
      "chance": 0.25,
      "output": {
        "item": "tfc_ie_addon:ore/poor_galena"
      }
    }
  ],
  "spoils": [
    {
      "chance": 0.2,
      "output": {
        "item": "tfc:rock/gravel/gabbro"
      }
    },
    {
      "chance": 0.8,
      "output": {
        "item": "tfc:rock/cobble/gabbro"
      }
    }
  ],
  "weight": 15
}